Workbook

Sheet Documentación
A1: PROYECTO FINAL - ANÁLISIS DE VENTAS RETAIL 2024
A3: INFORMACIÓN DEL PROYECTO
A4: Autor: | B4: Joseph (Senior Sales Manager)
A5: Fecha de elaboración: | B5: 16/01/2026
A6: Dataset: | B6: Ventas Retail - 500 transacciones (Ene-Dic 2024)
A8: PREGUNTAS DE NEGOCIO ANALIZADAS
A9: 1. | B9: ¿Cuál es la tendencia de ventas por región a lo largo del año?
A10: 2. | B10: ¿Qué categorías de productos generan mayor rentabilidad?
A11: 3. | B11: ¿Cuál es el desempeño comparativo de los canales de venta?
A12: 4. | B12: ¿Qué vendedores tienen mejor performance (ventas vs margen)?
A13: 5. | B13: ¿Cómo impactan los descuentos en el margen de ganancia?
A14: 6. | B14: ¿Cuáles son los productos estrella por categoría?
A16: METODOLOGÍA DE ANÁLISIS
A17: Limpieza de datos: | B17: Estandarización de formatos, validación de rangos, eliminación de duplicados
A18: Normalización: | B18: Cálculo de métricas derivadas (Subtotal, Total, Margen, % Margen)
A19: Análisis: | B19: Tablas dinámicas con segmentación múltiple, fórmulas condicionales
A20: Visualización: | B20: Gráficos dinámicos vinculados a tablas pivot
A22: FÓRMULAS AVANZADAS UTILIZADAS
A23: SUMIFS: | B23: Suma condicional múltiple para totales por región/categoría
A24: AVERAGEIFS: | B24: Promedio condicional para métricas de rendimiento
A25: COUNTIFS: | B25: Conteo condicional para análisis de frecuencia
A26: INDEX/MATCH: | B26: Búsqueda avanzada para ranking de productos
A27: IF anidados: | B27: Clasificación de rendimiento (Alto/Medio/Bajo)
A28: XLOOKUP: | B28: Búsqueda bidireccional para dashboard interactivo
A30: ESTRUCTURA DEL ARCHIVO
A31: Hoja 1: | B31: Documentación - Resumen metodológico y preguntas de análisis
A32: Hoja 2: | B32: Datos - Dataset completo con validaciones
A33: Hoja 3: | B33: Análisis - Tablas resumen con fórmulas avanzadas
A34: Hoja 4: | B34: Dashboard - Panel interactivo con KPIs y gráficos
A36: HALLAZGOS CLAVE (se actualizan con los datos)

Sheet Datos
A1: ID_Transaccion | B1: Fecha | C1: Region | D1: Categoria | E1: Producto | F1: Canal | G1: Vendedor | H1: Cantidad | I1: Precio_Unitario | J1: Descuento | K1: Costo_Unitario | L1: Subtotal | M1: Descuento_Valor | N1: Total_Venta | O1: Costo_Total | P1: Margen | Q1: Margen_Pct
A2: TRX-0001 | B2: 45363 | C2: Centro | D2: Electrónica | E2: Laptop | F2: Tienda Física | G2: Juan Martínez | H2: 5 | I2: 1031.34 | J2: 0 | K2: 564.79 | L2: =H2*I2 -> 5156.7 | M2: =L2*J2 -> 0 | N2: =L2-M2 -> 5156.7 | O2: =H2*K2 -> 2823.95 | P2: =N2-O2 -> 2332.75 | Q2: =IF(N2=0,0,P2/N2) -> 0.45237264
A3: TRX-0002 | B3: 45550 | C3: Norte | D3: Electrónica | E3: Laptop | F3: Tienda Física | G3: Juan Martínez | H3: 5 | I3: 945.29 | J3: 0.05 | K3: 547.33 | L3: =H3*I3 -> 4726.45 | M3: =L3*J3 -> 236.3225 | N3: =L3-M3 -> 4490.1275 | O3: =H3*K3 -> 2736.65 | P3: =N3-O3 -> 1753.4775 | Q3: =IF(N3=0,0,P3/N3) -> 0.39051842
A4: TRX-0003 | B4: 45434 | C4: Sur | D4: Deportes | E4: Zapatillas | F4: E-commerce | G4: Andrés Mora | H4: 1 | I4: 269.51 | J4: 0.05 | K4: 154.84 | L4: =H4*I4 -> 269.51 | M4: =L4*J4 -> 13.4755 | N4: =L4-M4 -> 256.0345 | O4: =H4*K4 -> 154.84 | P4: =N4-O4 -> 101.1945 | Q4: =IF(N4=0,0,P4/N4) -> 0.39523775
A5: TRX-0004 | B5: 45344 | C5: Sur | D5: Hogar | E5: Lámpara | F5: Tienda Física | G5: Pedro Ramírez | H5: 1 | I5: 270.97 | J5: 0.1 | K5: 165.8 | L5: =H5*I5 -> 270.97 | M5: =L5*J5 -> 27.097 | N5: =L5-M5 -> 243.873 | O5: =H5*K5 -> 165.8 | P5: =N5-O5 -> 78.073 | Q5: =IF(N5=0,0,P5/N5) -> 0.32013794
A6: TRX-0005 | B6: 45566 | C6: Norte | D6: Deportes | E6: Yoga Mat | F6: Marketplace | G6: Diego Hernández | H6: 4 | I6: 159.97 | J6: 0 | K6: 86.07 | L6: =H6*I6 -> 639.88 | M6: =L6*J6 -> 0 | N6: =L6-M6 -> 639.88 | O6: =H6*K6 -> 344.28 | P6: =N6-O6 -> 295.6 | Q6: =IF(N6=0,0,P6/N6) -> 0.46196162
A7: TRX-0006 | B7: 45315 | C7: Oeste | D7: Deportes | E7: Yoga Mat | F7: Tienda Física | G7: Carlos López | H7: 3 | I7: 245.8 | J7: 0 | K7: 150.88 | L7: =H7*I7 -> 737.4 | M7: =L7*J7 -> 0 | N7: =L7-M7 -> 737.4 | O7: =H7*K7 -> 452.64 | P7: =N7-O7 -> 284.76 | Q7: =IF(N7=0,0,P7/N7) -> 0.38616762
A8: TRX-0007 | B8: 45375 | C8: Centro | D8: Electrónica | E8: Auriculares | F8: E-commerce | G8: Pedro Ramírez | H8: 2 | I8: 796.92 | J8: 0.1 | K8: 458.59 | L8: =H8*I8 -> 1593.84 | M8: =L8*J8 -> 159.384 | N8: =L8-M8 -> 1434.456 | O8: =H8*K8 -> 917.18 | P8: =N8-O8 -> 517.276 | Q8: =IF(N8=0,0,P8/N8) -> 0.36060778
A9: TRX-0008 | B9: 45375 | C9: Sur | D9: Electrónica | E9: TV Smart | F9: Marketplace | G9: Juan Martínez | H9: 3 | I9: 855.85 | J9: 0.2 | K9: 389.33 | L9: =H9*I9 -> 2567.55 | M9: =L9*J9 -> 513.51 | N9: =L9-M9 -> 2054.04 | O9: =H9*K9 -> 1167.99 | P9: =N9-O9 -> 886.05 | Q9: =IF(N9=0,0,P9/N9) -> 0.4313694
A10: TRX-0009 | B10: 45497 | C10: Sur | D10: Hogar | E10: Sofá | F10: Tienda Física | G10: Pedro Ramírez | H10: 2 | I10: 319.97 | J10: 0.2 | K10: 198.09 | L10: =H10*I10 -> 639.94 | M10: =L10*J10 -> 127.988 | N10: =L10-M10 -> 511.952 | O10: =H10*K10 -> 396.18 | P10: =N10-O10 -> 115.772 | Q10: =IF(N10=0,0,P10/N10) -> 0.22613839
A11: TRX-0010 | B11: 45365 | C11: Este | D11: Hogar | E11: Mesa | F11: E-commerce | G11: Diego Hernández | H11: 2 | I11: 319.17 | J11: 0.2 | K11: 170.67 | L11: =H11*I11 -> 638.34 | M11: =L11*J11 -> 127.668 | N11: =L11-M11 -> 510.672 | O11: =H11*K11 -> 341.34 | P11: =N11-O11 -> 169.332 | Q11: =IF(N11=0,0,P11/N11) -> 0.33158662
A12: TRX-0011 | B12: 45404 | C12: Oeste | D12: Deportes | E12: Zapatillas | F12: E-commerce | G12: Pedro Ramírez | H12: 2 | I12: 299.57 | J12: 0.2 | K12: 156.79 | L12: =H12*I12 -> 599.14 | M12: =L12*J12 -> 119.828 | N12: =L12-M12 -> 479.312 | O12: =H12*K12 -> 313.58 | P12: =N12-O12 -> 165.732 | Q12: =IF(N12=0,0,P12/N12) -> 0.3457706
A13: TRX-0012 | B13: 45640 | C13: Sur | D13: Electrónica | E13: Laptop | F13: Marketplace | G13: María Rodríguez | H13: 1 | I13: 830.18 | J13: 0.15 | K13: 411.28 | L13: =H13*I13 -> 830.18 | M13: =L13*J13 -> 124.527 | N13: =L13-M13 -> 705.653 | O13: =H13*K13 -> 411.28 | P13: =N13-O13 -> 294.373 | Q13: =IF(N13=0,0,P13/N13) -> 0.41716396
... A501: TRX-0500 | B501: 45465 | C501: Sur | D501: Ropa | E501: Camisa | F501: Marketplace | G501: Sofia Torres | H501: 5 | I501: 160.88 | J501: 0 | K501: 70.82 | L501: =H501*I501 -> 804.4 | M501: =L501*J501 -> 0 | N501: =L501-M501 -> 804.4 | O501: =H501*K501 -> 354.1 | P501: =N501-O501 -> 450.3 | Q501: =IF(N501=0,0,P501/N501) -> 0.55979612

Sheet Análisis
A1: ANÁLISIS DETALLADO DE VENTAS
A3: 1. RESUMEN POR REGIÓN
A4: Región | B4: Total Ventas | C4: Transacciones | D4: Ticket Promedio | E4: Margen Total | F4: % Margen | G4: Ranking
A5: Norte | B5: =SUMIFS(Datos!$N:$N,Datos!$C:$C,A5) -> 100578.21 | C5: =COUNTIF(Datos!$C:$C,A5) -> 95 | D5: =IF(C5=0,0,B5/C5) -> 1058.718 | E5: =SUMIFS(Datos!$P:$P,Datos!$C:$C,A5) -> 42868.976 | F5: =IF(B5=0,0,E5/B5) -> 0.4262253 | G5: =RANK(B5,$B$5:$B$9,0) -> 3
A6: Sur | B6: =SUMIFS(Datos!$N:$N,Datos!$C:$C,A6) -> 97422.203 | C6: =COUNTIF(Datos!$C:$C,A6) -> 97 | D6: =IF(C6=0,0,B6/C6) -> 1004.3526 | E6: =SUMIFS(Datos!$P:$P,Datos!$C:$C,A6) -> 41177.834 | F6: =IF(B6=0,0,E6/B6) -> 0.42267401 | G6: =RANK(B6,$B$5:$B$9,0) -> 4
A7: Centro | B7: =SUMIFS(Datos!$N:$N,Datos!$C:$C,A7) -> 117794.13 | C7: =COUNTIF(Datos!$C:$C,A7) -> 97 | D7: =IF(C7=0,0,B7/C7) -> 1214.3724 | E7: =SUMIFS(Datos!$P:$P,Datos!$C:$C,A7) -> 50996.025 | F7: =IF(B7=0,0,E7/B7) -> 0.43292503 | G7: =RANK(B7,$B$5:$B$9,0) -> 1
A8: Este | B8: =SUMIFS(Datos!$N:$N,Datos!$C:$C,A8) -> 96230.39 | C8: =COUNTIF(Datos!$C:$C,A8) -> 99 | D8: =IF(C8=0,0,B8/C8) -> 972.02415 | E8: =SUMIFS(Datos!$P:$P,Datos!$C:$C,A8) -> 40433.71 | F8: =IF(B8=0,0,E8/B8) -> 0.4201761 | G8: =RANK(B8,$B$5:$B$9,0) -> 5
A9: Oeste | B9: =SUMIFS(Datos!$N:$N,Datos!$C:$C,A9) -> 101771.99 | C9: =COUNTIF(Datos!$C:$C,A9) -> 112 | D9: =IF(C9=0,0,B9/C9) -> 908.67846 | E9: =SUMIFS(Datos!$P:$P,Datos!$C:$C,A9) -> 42602.597 | F9: =IF(B9=0,0,E9/B9) -> 0.41860829 | G9: =RANK(B9,$B$5:$B$9,0) -> 2
A10: TOTAL | B10: =SUM(B5:B9) -> 513796.91 | C10: =SUM(C5:C9) -> 500 | D10: =IF(C10=0,0,B10/C10) -> 1027.5938 | E10: =SUM(E5:E9) -> 218079.14 | F10: =IF(B10=0,0,E10/B10) -> 0.42444619
A13: 2. RESUMEN POR CATEGORÍA
A14: Categoría | B14: Total Ventas | C14: Unidades | D14: Precio Prom. | E14: Margen Total | F14: % Margen | G14: Clasificación
A15: Electrónica | B15: =SUMIFS(Datos!$N:$N,Datos!$D:$D,A15) -> 275932.21 | C15: =SUMIFS(Datos!$H:$H,Datos!$D:$D,A15) -> 338 | D15: =AVERAGEIFS(Datos!$I:$I,Datos!$D:$D,A15) -> 893.17875 | E15: =SUMIFS(Datos!$P:$P,Datos!$D:$D,A15) -> 118704.98 | F15: =IF(B15=0,0,E15/B15) -> 0.43019617 | G15: =IF(F15>0.4,"Alto",IF(F15>0.3,"Medio","Bajo")) -> Alto
A16: Ropa | B16: =SUMIFS(Datos!$N:$N,Datos!$D:$D,A16) -> 40405.118 | C16: =SUMIFS(Datos!$H:$H,Datos!$D:$D,A16) -> 331 | D16: =AVERAGEIFS(Datos!$I:$I,Datos!$D:$D,A16) -> 135.51776 | E16: =SUMIFS(Datos!$P:$P,Datos!$D:$D,A16) -> 17473.478 | F16: =IF(B16=0,0,E16/B16) -> 0.43245705 | G16: =IF(F16>0.4,"Alto",IF(F16>0.3,"Medio","Bajo")) -> Alto
A17: Hogar | B17: =SUMIFS(Datos!$N:$N,Datos!$D:$D,A17) -> 112673.24 | C17: =SUMIFS(Datos!$H:$H,Datos!$D:$D,A17) -> 316 | D17: =AVERAGEIFS(Datos!$I:$I,Datos!$D:$D,A17) -> 395.34641 | E17: =SUMIFS(Datos!$P:$P,Datos!$D:$D,A17) -> 46808.887 | F17: =IF(B17=0,0,E17/B17) -> 0.41543927 | G17: =IF(F17>0.4,"Alto",IF(F17>0.3,"Medio","Bajo")) -> Alto
A18: Alimentos | B18: =SUMIFS(Datos!$N:$N,Datos!$D:$D,A18) -> 20967.118 | C18: =SUMIFS(Datos!$H:$H,Datos!$D:$D,A18) -> 857 | D18: =AVERAGEIFS(Datos!$I:$I,Datos!$D:$D,A18) -> 27.315125 | E18: =SUMIFS(Datos!$P:$P,Datos!$D:$D,A18) -> 8237.568 | F18: =IF(B18=0,0,E18/B18) -> 0.39288032 | G18: =IF(F18>0.4,"Alto",IF(F18>0.3,"Medio","Bajo")) -> Medio
A19: Deportes | B19: =SUMIFS(Datos!$N:$N,Datos!$D:$D,A19) -> 63819.227 | C19: =SUMIFS(Datos!$H:$H,Datos!$D:$D,A19) -> 319 | D19: =AVERAGEIFS(Datos!$I:$I,Datos!$D:$D,A19) -> 219.90434 | E19: =SUMIFS(Datos!$P:$P,Datos!$D:$D,A19) -> 26854.227 | F19: =IF(B19=0,0,E19/B19) -> 0.42078584 | G19: =IF(F19>0.4,"Alto",IF(F19>0.3,"Medio","Bajo")) -> Alto
A23: 3. RESUMEN POR CANAL DE VENTA
A24: Canal | B24: Total Ventas | C24: Transacciones | D24: % del Total | E24: Margen Prom. | F24: Tendencia
A25: Tienda Física | B25: =SUMIFS(Datos!$N:$N,Datos!$F:$F,A25) -> 173424.23 | C25: =COUNTIF(Datos!$F:$F,A25) -> 164 | D25: =IF($B$28=0,0,B25/$B$28) -> 0.3375346 | E25: =AVERAGEIFS(Datos!$Q:$Q,Datos!$F:$F,A25) -> 0.41883259 | F25: =IF(B25>AVERAGE($B$25:$B$27),"↑ Arriba","↓ Abajo") -> ↑ Arriba
A26: E-commerce | B26: =SUMIFS(Datos!$N:$N,Datos!$F:$F,A26) -> 167146.68 | C26: =COUNTIF(Datos!$F:$F,A26) -> 167 | D26: =IF($B$28=0,0,B26/$B$28) -> 0.32531663 | E26: =AVERAGEIFS(Datos!$Q:$Q,Datos!$F:$F,A26) -> 0.40859209 | F26: =IF(B26>AVERAGE($B$25:$B$27),"↑ Arriba","↓ Abajo") -> ↓ Abajo
A27: Marketplace | B27: =SUMIFS(Datos!$N:$N,Datos!$F:$F,A27) -> 173226 | C27: =COUNTIF(Datos!$F:$F,A27) -> 169 | D27: =IF($B$28=0,0,B27/$B$28) -> 0.33714877 | E27: =AVERAGEIFS(Datos!$Q:$Q,Datos!$F:$F,A27) -> 0.41352918 | F27: =IF(B27>AVERAGE($B$25:$B$27),"↑ Arriba","↓ Abajo") -> ↑ Arriba
A28: TOTAL | B28: =SUM(B25:B27) -> 513796.91 | C28: =SUM(C25:C27) -> 500
A31: 4. TOP 10 VENDEDORES
A32: Vendedor | B32: Total Ventas | C32: Transacciones | D32: Margen Total | E32: % Margen | F32: Performance
A33: Ana García | B33: =SUMIFS(Datos!$N:$N,Datos!$G:$G,A33) -> 39805.851 | C33: =COUNTIF(Datos!$G:$G,A33) -> 35 | D33: =SUMIFS(Datos!$P:$P,Datos!$G:$G,A33) -> 14682.591 | E33: =IF(B33=0,0,D33/B33) -> 0.36885509 | F33: =IF(AND(B33>AVERAGE($B$33:$B$42),E33>AVERAGE($E$33:$E$42)),"★★★ Excelente",IF(OR(B33>AVERAGE($B$33:$B$42),E33>AVERAGE($E$33:$E$42)),"★★ Bueno","★ Regular")) -> ★ Regular
A34: Carlos López | B34: =SUMIFS(Datos!$N:$N,Datos!$G:$G,A34) -> 58867.334 | C34: =COUNTIF(Datos!$G:$G,A34) -> 54 | D34: =SUMIFS(Datos!$P:$P,Datos!$G:$G,A34) -> 24504.674 | E34: =IF(B34=0,0,D34/B34) -> 0.41626947 | F34: =IF(AND(B34>AVERAGE($B$33:$B$42),E34>AVERAGE($E$33:$E$42)),"★★★ Excelente",IF(OR(B34>AVERAGE($B$33:$B$42),E34>AVERAGE($E$33:$E$42)),"★★ Bueno","★ Regular")) -> ★★ Bueno
A35: María Rodríguez | B35: =SUMIFS(Datos!$N:$N,Datos!$G:$G,A35) -> 47082.677 | C35: =COUNTIF(Datos!$G:$G,A35) -> 47 | D35: =SUMIFS(Datos!$P:$P,Datos!$G:$G,A35) -> 19899.027 | E35: =IF(B35=0,0,D35/B35) -> 0.42264009 | F35: =IF(AND(B35>AVERAGE($B$33:$B$42),E35>AVERAGE($E$33:$E$42)),"★★★ Excelente",IF(OR(B35>AVERAGE($B$33:$B$42),E35>AVERAGE($E$33:$E$42)),"★★ Bueno","★ Regular")) -> ★★ Bueno
A36: Juan Martínez | B36: =SUMIFS(Datos!$N:$N,Datos!$G:$G,A36) -> 63466.126 | C36: =COUNTIF(Datos!$G:$G,A36) -> 54 | D36: =SUMIFS(Datos!$P:$P,Datos!$G:$G,A36) -> 27511.457 | E36: =IF(B36=0,0,D36/B36) -> 0.43348252 | F36: =IF(AND(B36>AVERAGE($B$33:$B$42),E36>AVERAGE($E$33:$E$42)),"★★★ Excelente",IF(OR(B36>AVERAGE($B$33:$B$42),E36>AVERAGE($E$33:$E$42)),"★★ Bueno","★ Regular")) -> ★★★ Excelente
A37: Laura Sánchez | B37: =SUMIFS(Datos!$N:$N,Datos!$G:$G,A37) -> 63035.717 | C37: =COUNTIF(Datos!$G:$G,A37) -> 46 | D37: =SUMIFS(Datos!$P:$P,Datos!$G:$G,A37) -> 28776.007 | E37: =IF(B37=0,0,D37/B37) -> 0.45650321 | F37: =IF(AND(B37>AVERAGE($B$33:$B$42),E37>AVERAGE($E$33:$E$42)),"★★★ Excelente",IF(OR(B37>AVERAGE($B$33:$B$42),E37>AVERAGE($E$33:$E$42)),"★★ Bueno","★ Regular")) -> ★★★ Excelente
A38: Pedro Ramírez | B38: =SUMIFS(Datos!$N:$N,Datos!$G:$G,A38) -> 60917.868 | C38: =COUNTIF(Datos!$G:$G,A38) -> 59 | D38: =SUMIFS(Datos!$P:$P,Datos!$G:$G,A38) -> 26498.189 | E38: =IF(B38=0,0,D38/B38) -> 0.4349822 | F38: =IF(AND(B38>AVERAGE($B$33:$B$42),E38>AVERAGE($E$33:$E$42)),"★★★ Excelente",IF(OR(B38>AVERAGE($B$33:$B$42),E38>AVERAGE($E$33:$E$42)),"★★ Bueno","★ Regular")) -> ★★★ Excelente
A39: Sofia Torres | B39: =SUMIFS(Datos!$N:$N,Datos!$G:$G,A39) -> 54764.676 | C39: =COUNTIF(Datos!$G:$G,A39) -> 58 | D39: =SUMIFS(Datos!$P:$P,Datos!$G:$G,A39) -> 22877.796 | E39: =IF(B39=0,0,D39/B39) -> 0.41774731 | F39: =IF(AND(B39>AVERAGE($B$33:$B$42),E39>AVERAGE($E$33:$E$42)),"★★★ Excelente",IF(OR(B39>AVERAGE($B$33:$B$42),E39>AVERAGE($E$33:$E$42)),"★★ Bueno","★ Regular")) -> ★★ Bueno
A40: Diego Hernández | B40: =SUMIFS(Datos!$N:$N,Datos!$G:$G,A40) -> 51424.498 | C40: =COUNTIF(Datos!$G:$G,A40) -> 64 | D40: =SUMIFS(Datos!$P:$P,Datos!$G:$G,A40) -> 22410.158 | E40: =IF(B40=0,0,D40/B40) -> 0.43578758 | F40: =IF(AND(B40>AVERAGE($B$33:$B$42),E40>AVERAGE($E$33:$E$42)),"★★★ Excelente",IF(OR(B40>AVERAGE($B$33:$B$42),E40>AVERAGE($E$33:$E$42)),"★★ Bueno","★ Regular")) -> ★★★ Excelente
A41: Valentina Cruz | B41: =SUMIFS(Datos!$N:$N,Datos!$G:$G,A41) -> 38712.342 | C41: =COUNTIF(Datos!$G:$G,A41) -> 41 | D41: =SUMIFS(Datos!$P:$P,Datos!$G:$G,A41) -> 15360.932 | E41: =IF(B41=0,0,D41/B41) -> 0.39679676 | F41: =IF(AND(B41>AVERAGE($B$33:$B$42),E41>AVERAGE($E$33:$E$42)),"★★★ Excelente",IF(OR(B41>AVERAGE($B$33:$B$42),E41>AVERAGE($E$33:$E$42)),"★★ Bueno","★ Regular")) -> ★ Regular
A42: Andrés Mora | B42: =SUMIFS(Datos!$N:$N,Datos!$G:$G,A42) -> 35719.823 | C42: =COUNTIF(Datos!$G:$G,A42) -> 42 | D42: =SUMIFS(Datos!$P:$P,Datos!$G:$G,A42) -> 15558.314 | E42: =IF(B42=0,0,D42/B42) -> 0.43556524 | F42: =IF(AND(B42>AVERAGE($B$33:$B$42),E42>AVERAGE($E$33:$E$42)),"★★★ Excelente",IF(OR(B42>AVERAGE($B$33:$B$42),E42>AVERAGE($E$33:$E$42)),"★★ Bueno","★ Regular")) -> ★★ Bueno

Sheet Dashboard
A1: DASHBOARD DE VENTAS - ANÁLISIS EJECUTIVO 2024
A3: INDICADORES CLAVE (KPIs)
A4: Total Ventas | C4: Margen Total | E4: % Margen Global | G4: Ticket Promedio | I4: Total Transacciones
A5: =SUM(Datos!N:N) -> 513796.91 | C5: =SUM(Datos!P:P) -> 218079.14 | E5: =IF(A5=0,0,C5/A5) -> 0.42444619 | G5: =IF(I5=0,0,A5/I5) -> 1027.5938 | I5: =COUNTA(Datos!A:A)-1 -> 500
A8: FILTROS INTERACTIVOS | D8: VENTAS POR REGIÓN | H8: VENTAS POR CATEGORÍA
A9: Seleccionar Región: | B9: Todas | D9: Región | E9: Ventas | F9: Margen | H9: Categoría | I9: Ventas
A10: Seleccionar Categoría: | B10: Todas | D10: Norte | E10: =SUMIFS(Datos!$N:$N,Datos!$C:$C,D10) -> 100578.21 | F10: =SUMIFS(Datos!$P:$P,Datos!$C:$C,D10) -> 42868.976 | H10: Electrónica | I10: =SUMIFS(Datos!$N:$N,Datos!$D:$D,H10) -> 275932.21
A11: Seleccionar Canal: | B11: Todos | D11: Sur | E11: =SUMIFS(Datos!$N:$N,Datos!$C:$C,D11) -> 97422.203 | F11: =SUMIFS(Datos!$P:$P,Datos!$C:$C,D11) -> 41177.834 | H11: Ropa | I11: =SUMIFS(Datos!$N:$N,Datos!$D:$D,H11) -> 40405.118
D12: Centro | E12: =SUMIFS(Datos!$N:$N,Datos!$C:$C,D12) -> 117794.13 | F12: =SUMIFS(Datos!$P:$P,Datos!$C:$C,D12) -> 50996.025 | H12: Hogar | I12: =SUMIFS(Datos!$N:$N,Datos!$D:$D,H12) -> 112673.24
A13: RESULTADOS SEGÚN FILTROS | D13: Este | E13: =SUMIFS(Datos!$N:$N,Datos!$C:$C,D13) -> 96230.39 | F13: =SUMIFS(Datos!$P:$P,Datos!$C:$C,D13) -> 40433.71 | H13: Alimentos | I13: =SUMIFS(Datos!$N:$N,Datos!$D:$D,H13) -> 20967.118
A14: Métrica | B14: Valor | D14: Oeste | E14: =SUMIFS(Datos!$N:$N,Datos!$C:$C,D14) -> 101771.99 | F14: =SUMIFS(Datos!$P:$P,Datos!$C:$C,D14) -> 42602.597 | H14: Deportes | I14: =SUMIFS(Datos!$N:$N,Datos!$D:$D,H14) -> 63819.227
A15: Ventas Filtradas | B15: =SUMPRODUCT((Datos!$N$2:$N$501)*((Datos!$C$2:$C$501=$B$9)+($B$9="Todas"))*((Datos!$D$2:$D$501=$B$10)+($B$10="Todas"))*((Datos!$F$2:$F$501=$B$11)+($B$11="Todos"))) -> 513796.91
A16: Transacciones | B16: =SUMPRODUCT(((Datos!$C$2:$C$501=$B$9)+($B$9="Todas"))*((Datos!$D$2:$D$501=$B$10)+($B$10="Todas"))*((Datos!$F$2:$F$501=$B$11)+($B$11="Todos"))) -> 500
A17: Margen Filtrado | B17: =SUMPRODUCT((Datos!$P$2:$P$501)*((Datos!$C$2:$C$501=$B$9)+($B$9="Todas"))*((Datos!$D$2:$D$501=$B$10)+($B$10="Todas"))*((Datos!$F$2:$F$501=$B$11)+($B$11="Todos"))) -> 218079.14
A18: % del Total | B18: =IF(OR(B15=0,A5=0),0,B15/A5) -> 1
A22: TENDENCIA MENSUAL DE VENTAS
A23: Mes | B23: Ventas
A24: Ene | B24: =SUMIFS(Datos!$N:$N,Datos!$B:$B,">="&DATE(2024,1,1),Datos!$B:$B,"<"&DATE(2024,2,1)) -> 40246.024
A25: Feb | B25: =SUMIFS(Datos!$N:$N,Datos!$B:$B,">="&DATE(2024,2,1),Datos!$B:$B,"<"&DATE(2024,3,1)) -> 49201.894
A26: Mar | B26: =SUMIFS(Datos!$N:$N,Datos!$B:$B,">="&DATE(2024,3,1),Datos!$B:$B,"<"&DATE(2024,4,1)) -> 47641.333
A27: Abr | B27: =SUMIFS(Datos!$N:$N,Datos!$B:$B,">="&DATE(2024,4,1),Datos!$B:$B,"<"&DATE(2024,5,1)) -> 56960.094
A28: May | B28: =SUMIFS(Datos!$N:$N,Datos!$B:$B,">="&DATE(2024,5,1),Datos!$B:$B,"<"&DATE(2024,6,1)) -> 30830.305
A29: Jun | B29: =SUMIFS(Datos!$N:$N,Datos!$B:$B,">="&DATE(2024,6,1),Datos!$B:$B,"<"&DATE(2024,7,1)) -> 43807.235
A30: Jul | B30: =SUMIFS(Datos!$N:$N,Datos!$B:$B,">="&DATE(2024,7,1),Datos!$B:$B,"<"&DATE(2024,8,1)) -> 50082.689
A31: Ago | B31: =SUMIFS(Datos!$N:$N,Datos!$B:$B,">="&DATE(2024,8,1),Datos!$B:$B,"<"&DATE(2024,9,1)) -> 37618.041
A32: Sep | B32: =SUMIFS(Datos!$N:$N,Datos!$B:$B,">="&DATE(2024,9,1),Datos!$B:$B,"<"&DATE(2024,10,1)) -> 34991.82
A33: Oct | B33: =SUMIFS(Datos!$N:$N,Datos!$B:$B,">="&DATE(2024,10,1),Datos!$B:$B,"<"&DATE(2024,11,1)) -> 53360.239
A34: Nov | B34: =SUMIFS(Datos!$N:$N,Datos!$B:$B,">="&DATE(2024,11,1),Datos!$B:$B,"<"&DATE(2024,12,1)) -> 34662.537
A35: Dic | B35: =SUMIFS(Datos!$N:$N,Datos!$B:$B,">="&DATE(2024,12,1),Datos!$B:$B,"<"&DATE(2024,13,1)) -> 34394.699
H37: RESUMEN EJECUTIVO
H38: Mejor Región: | I38: =INDEX(Análisis!A5:A9,MATCH(MAX(Análisis!B5:B9),Análisis!B5:B9,0)) -> Centro
H39: Mejor Categoría: | I39: =INDEX(Análisis!A15:A19,MATCH(MAX(Análisis!B15:B19),Análisis!B15:B19,0)) -> Electrónica
H40: Canal Líder: | I40: =INDEX(Análisis!A25:A27,MATCH(MAX(Análisis!B25:B27),Análisis!B25:B27,0)) -> Tienda Física
H41: Top Vendedor: | I41: =INDEX(Análisis!A33:A42,MATCH(MAX(Análisis!B33:B42),Análisis!B33:B42,0)) -> Juan Martínez
